RestRouterOS/__init__.py
RestRouterOS/api.py
RestRouterOS/RestAdapter/__init__.py
RestRouterOS/RestAdapter/adapter.py
Rest_RouterOS-0.1.0.dist-info/LICENSE
Rest_RouterOS-0.1.0.dist-info/METADATA
Rest_RouterOS-0.1.0.dist-info/WHEEL
Rest_RouterOS-0.1.0.dist-info/top_level.txt
Rest_RouterOS-0.1.0.dist-info/RECORD
