Metadata-Version: 2.2
Name: Rest-RouterOS
Version: 0.1.0
Summary: A python module for RouterOS REST API
Home-page: https://github.com/silvertoken/rest-routeros
Author: Silvertoken
Author-email: silvertoken <1569232+silvertoken@users.noreply.github.com>
Project-URL: Homepage, https://github.com/silvertoken/rest-routeros
Project-URL: Issues, https://github.com/silvertoken/rest-routeros/issues
Classifier: Programming Language :: Python :: 3
Classifier: Operating System :: OS Independent
Requires-Python: >=3.13
License-File: LICENSE
Dynamic: author
Dynamic: home-page
